btpbap/__init__.py
btpbap/__main__.py
btpbap/helper.py
btpbap/pce.py
btpbap/pse.py
btpbap/pytransform/__init__.py
btpbap/pytransform/platforms/linux/aarch64/_pytransform.so
btpbap/pytransform/platforms/linux/x86_64/_pytransform.so
btpbap-0.0.1.dist-info/LICENSE.txt
btpbap-0.0.1.dist-info/METADATA
btpbap-0.0.1.dist-info/WHEEL
btpbap-0.0.1.dist-info/top_level.txt
btpbap-0.0.1.dist-info/RECORD
